jkl_serialization/__init__.py
jkl_serialization/test_jkl_serialization.py
jkl_serialization-0.0.1.dist-info/LICENSE
jkl_serialization-0.0.1.dist-info/METADATA
jkl_serialization-0.0.1.dist-info/WHEEL
jkl_serialization-0.0.1.dist-info/top_level.txt
jkl_serialization-0.0.1.dist-info/RECORD
