Metadata-Version: 2.1
Name: jkl-serialization
Version: 0.0.1
Summary: (De)Serialization of JKL objects
Home-page: https://github.com/daanknoope/jkl-serialization
Author: Daan Knoope
Author-email: daan@knoope.dev
License: UNKNOWN
Platform: UNKNOWN
Classifier: Programming Language :: Python :: 3
Classifier: License :: OSI Approved :: MIT License
Classifier: Operating System :: OS Independent
Requires-Python: >3.6
